pivpy/__init__.py
pivpy/compute_funcs.py
pivpy/davis_readim.py
pivpy/graphics.py
pivpy/graphics_utils.py
pivpy/inter.py
pivpy/interfacing.py
pivpy/io.py
pivpy/pivmat_compat.py
pivpy/pivpy.py
pivpy/update.py
pivpy/data/Insight/Run000001.T000.D000.P000.H001.L.vec
pivpy/data/Insight/Run000002.T000.D000.P000.H001.L.vec
pivpy/data/Insight/Run000003.T000.D000.P000.H001.L.vec
pivpy/data/Insight/Run000004.T000.D000.P000.H001.L.vec
pivpy/data/Insight/Run000005.T000.D000.P000.H001.L.vec
pivpy/data/PIVMAT_jet/B00001.VC7
pivpy/data/PIVMAT_jet/B00002.VC7
pivpy/data/PIVMAT_jet/B00003.VC7
pivpy/data/PIVMAT_jet/readme.txt
pivpy/data/PIV_Challenge/B00001.txt
pivpy/data/PIV_Challenge/B00002.txt
pivpy/data/day2/day2a005000.T000.D000.P003.H001.L.vec
pivpy/data/day2/day2a005001.T000.D000.P003.H001.L.vec
pivpy/data/day2/day2a005002.T000.D000.P003.H001.L.vec
pivpy/data/day2/day2a005003.T000.D000.P003.H001.L.vec
pivpy/data/day2/day2a005004.T000.D000.P003.H001.L.vec
pivpy/data/day2/day2a005005.T000.D000.P003.H001.L.vec
pivpy/data/interTest/testInterCreates_nc.nc
pivpy/data/openpiv_txt/exp1_001_b.txt
pivpy/data/openpiv_txt/interTest.txt
pivpy/data/openpiv_txt/Gamma1_Gamma2_tutorial_notebook/OpenPIVtxtFilePair0.txt
pivpy/data/openpiv_txt/Gamma1_Gamma2_tutorial_notebook/OpenPIVtxtFilePair1.txt
pivpy/data/openpiv_txt/Gamma1_Gamma2_tutorial_notebook/StrongVortex/CREDIT.txt
pivpy/data/openpiv_txt/Gamma1_Gamma2_tutorial_notebook/StrongVortex/A/PIVchallengeCaseAframeA.jpg
pivpy/data/openpiv_txt/Gamma1_Gamma2_tutorial_notebook/StrongVortex/A/PIVchallengeCaseAframeB.jpg
pivpy/data/openpiv_txt/Gamma1_Gamma2_tutorial_notebook/StrongVortex/A/PIVchallengeCaseAvelField.txt
pivpy/data/openpiv_txt/Gamma1_Gamma2_tutorial_notebook/StrongVortex/A/readme.txt
pivpy/data/openpiv_txt/Gamma1_Gamma2_tutorial_notebook/StrongVortex/B/PIVchallengeCaseBframeA.jpg
pivpy/data/openpiv_txt/Gamma1_Gamma2_tutorial_notebook/StrongVortex/B/PIVchallengeCaseBframeB.jpg
pivpy-0.1.1.dist-info/licenses/LICENSE
pivpy-0.1.1.dist-info/METADATA
pivpy-0.1.1.dist-info/WHEEL
pivpy-0.1.1.dist-info/top_level.txt
pivpy-0.1.1.dist-info/RECORD
