Metadata-Version: 2.4
Name: pivpy
Version: 0.1.1
Summary: Python package for post-processing PIV results
Author-email: Alex Liberzon and Ron Shnapp <alex.liberzon@gmail.com>
License-Expression: MIT
Project-URL: Homepage, https://github.com/alexlib/pivpy
Project-URL: Bug Tracker, https://github.com/alexlib/pivpy/issues
Keywords: example documentation tutorial
Classifier: Programming Language :: Python :: 3
Classifier: Operating System :: OS Independent
Requires-Python: >=3.7
License-File: LICENSE
Requires-Dist: numpy
Requires-Dist: scipy
Requires-Dist: xarray
Requires-Dist: matplotlib
Requires-Dist: pytest
Requires-Dist: vortexfitting
Requires-Dist: h5py
Requires-Dist: nbformat>=5.8.0
Requires-Dist: nbconvert>=7.6.0
Requires-Dist: ipykernel>=6.16.2
Requires-Dist: setuptools>=68.0.0
Requires-Dist: openpiv>=0.25.1
Provides-Extra: lvpyio
Requires-Dist: lvpyio; extra == "lvpyio"
Provides-Extra: readim
Requires-Dist: readim; extra == "readim"
Provides-Extra: netcdf
Requires-Dist: netcdf4; extra == "netcdf"
Provides-Extra: vortexfitting
Requires-Dist: vortexfitting; extra == "vortexfitting"
Provides-Extra: h5py
Requires-Dist: h5py; extra == "h5py"
Provides-Extra: full
Requires-Dist: lvpyio; extra == "full"
Requires-Dist: readim; extra == "full"
Requires-Dist: netcdf4; extra == "full"
Requires-Dist: vortexfitting; extra == "full"
Requires-Dist: h5py; extra == "full"
Dynamic: license-file
